deqr/__init__.py
deqr/binarize.pxd
deqr/binarize.pyx
deqr/datatypes.py
deqr/image.py
deqr/qrdec.pyx
deqr/qrdecdecl.pxd
deqr/quirc.pyx
deqr/quircdecl.pxd
deqr/version.py
deqr/binarize.c
deqr/binarize.cpython-313t-darwin.so
deqr/qrdec.c
deqr/qrdec.cpython-313t-darwin.so
deqr/quirc.c
deqr/quirc.cpython-313t-darwin.so
deqr-0.2.4.dist-info/COPYING
deqr-0.2.4.dist-info/LICENSE.isc
deqr-0.2.4.dist-info/LICENSE.lgpl
deqr-0.2.4.dist-info/METADATA
deqr-0.2.4.dist-info/WHEEL
deqr-0.2.4.dist-info/RECORD
